{
  "action": {
    "description": "Signed by Governor on 03/31/26    Session Law Chapter 258    Effective: 03/31/2026 SECTION 7-9;    07/01/2026 SECTION 1-6",
    "occurred_at": "2026-04-01",
    "jurisdiction_id": "~{\"classification\": \"upper\"}",
    "session_id": "2026",
    "entity_type": "bill",
    "classifications": [
      "became-law",
      "executive-signature"
    ],
    "related_entities": [],
    "sources": [
      {
        "url": "https://legislature.idaho.gov/sessioninfo/2026/legislation/S1427/",
        "note": ""
      }
    ]
  },
  "bill_id": "S 1427"
}