{
  "legislative_session": "2026",
  "identifier": "H 0660",
  "title": "IMMIGRATION STATUS AND NATIONALITY OF ARRESTED INDIVIDUALS \u2013 Adds to existing law to establish provisions regarding the immigration status and nationality of arrested individuals.",
  "from_organization": "~{\"classification\": \"lower\"}",
  "classification": [
    "bill"
  ],
  "subject": [
    "CRIMINAL BACKGROUND CHECKS",
    "GOVERNMENT",
    "IMMIGRATION AND IMMIGRANTS",
    "INTERNATIONAL RELATIONS",
    "LAW ENFORCEMENT",
    "REPORTS"
  ],
  "abstracts": [],
  "other_titles": [
    {
      "note": "short title",
      "title": "Immigration status, arrested"
    }
  ],
  "other_identifiers": [
    {
      "identifier": "ocd-bill-id-2026-h660"
    }
  ],
  "actions": [
    {
      "description": "Introduced, read first time, referred to JRA for Printing",
      "date": "2026-02-13",
      "organization_id": "~{\"classification\": \"lower\"}",
      "classification": [
        "introduction",
        "reading-1",
        "referral-committee"
      ],
      "related_entities": [],
      "_processing": {
        "log_file_created": "2026-07-15T03:54:51Z"
      }
    },
    {
      "description": "Reported Printed and Referred to Judiciary, Rules & Administration",
      "date": "2026-02-16",
      "organization_id": "~{\"classification\": \"lower\"}",
      "classification": [],
      "related_entities": [],
      "_processing": {
        "log_file_created": "2026-07-15T03:54:51Z"
      }
    },
    {
      "description": "Reported out of Committee, Returned to the Desk for re-referral",
      "date": "2026-03-11",
      "organization_id": "~{\"classification\": \"lower\"}",
      "classification": [],
      "related_entities": [],
      "_processing": {
        "log_file_created": "2026-07-15T03:54:51Z"
      }
    },
    {
      "description": "Referred to Local Government",
      "date": "2026-03-11",
      "organization_id": "~{\"classification\": \"lower\"}",
      "classification": [],
      "related_entities": [],
      "_processing": {
        "log_file_created": "2026-07-15T03:54:51Z"
      }
    },
    {
      "description": "Reported out of Committee with Do Pass Recommendation, Filed for Second Reading",
      "date": "2026-03-16",
      "organization_id": "~{\"classification\": \"lower\"}",
      "classification": [
        "committee-passage-favorable"
      ],
      "related_entities": [],
      "_processing": {
        "log_file_created": "2026-07-15T03:54:51Z"
      }
    },
    {
      "description": "Read second time; Filed for Third Reading",
      "date": "2026-03-17",
      "organization_id": "~{\"classification\": \"lower\"}",
      "classification": [
        "reading-2"
      ],
      "related_entities": [],
      "_processing": {
        "log_file_created": "2026-07-15T03:54:51Z"
      }
    },
    {
      "description": "Read Third Time in Full \u2013 PASSED - 40-30-0AYES \u2013 Alfieri, Barbieri, Beiswenger, Boyle, Bruce, Burgoyne, Cannon, Cayler, Cornilles, Crane(12), Crane(13), Ehardt, Ehlers, Fuhriman, Harris, Hawkins, Healey, Hill, Holtzclaw, Hostetler, Leavitt, Marmon, Mendive, Mitchell, Monks, Palmer, Pickett, Price, Rasor, Redman, Scott, Shepherd, Shirts, Skaug(Chadwick), Tanner(13), Tanner(14), Thompson, Vander Woude, Wisniewski, Mr. SpeakerNAYS \u2013 Berch, Bingham, Cheatum, Church, Dygert, Egbert, Erickson, Furniss, Galaviz, Gannon, Garner, Green, Hall(Stone), Handy, Haws, Manwaring, Mathias, McCann, Mickelsen, Miller, Nelsen, Petzke, Pohanka, Raybould, Raymond, Rubel, Sauter, Veile, Weber, WheelerAbsent \u2013 NoneFloor Sponsor - HawkinsTitle apvd - to Senate",
      "date": "2026-03-18",
      "organization_id": "~{\"classification\": \"lower\"}",
      "classification": [
        "passage",
        "reading-3"
      ],
      "related_entities": [],
      "_processing": {
        "log_file_created": "2026-07-15T03:54:51Z"
      }
    },
    {
      "description": "Received from the House passed; filed for first reading",
      "date": "2026-03-19",
      "organization_id": "~{\"classification\": \"upper\"}",
      "classification": [],
      "related_entities": [],
      "_processing": {
        "log_file_created": "2026-07-15T03:54:51Z"
      }
    },
    {
      "description": "Introduced, read first time; referred to: Judiciary & Rules",
      "date": "2026-03-19",
      "organization_id": "~{\"classification\": \"upper\"}",
      "classification": [
        "introduction"
      ],
      "related_entities": [],
      "_processing": {
        "log_file_created": "2026-07-15T03:54:51Z"
      }
    }
  ],
  "sponsorships": [
    {
      "name": "LOCAL GOVERNMENT COMMITTEE",
      "classification": "primary",
      "entity_type": "organization",
      "primary": true,
      "person_id": null,
      "organization_id": "~{\"chamber\": \"lower\", \"name\": \"LOCAL GOVERNMENT COMMITTEE\"}"
    }
  ],
  "related_bills": [],
  "versions": [
    {
      "note": "Bill Text",
      "links": [
        {
          "url": "https://legislature.idaho.gov/wp-content/uploads/sessioninfo/2026/legislation/H0660.pdf",
          "media_type": "application/pdf"
        }
      ],
      "date": "",
      "classification": ""
    }
  ],
  "documents": [
    {
      "note": "Statement of Purpose / Fiscal Note",
      "links": [
        {
          "url": "https://legislature.idaho.gov/wp-content/uploads/sessioninfo/2026/legislation/H0660SOP.pdf",
          "media_type": "application/pdf"
        }
      ],
      "date": "",
      "classification": ""
    }
  ],
  "citations": [],
  "sources": [
    {
      "url": "https://legislature.idaho.gov/sessioninfo/2026/legislation/H0660/",
      "note": ""
    }
  ],
  "extras": {},
  "jurisdiction": {
    "id": "ocd-jurisdiction/country:us/state:id/government",
    "name": "Idaho",
    "classification": "state",
    "division_id": "ocd-division/country:us/state:id"
  },
  "_processing": {
    "logs_latest_update": "2026-07-15T03:54:51Z"
  }
}